[
	{
		"__TYPE__": "SharedSliceContent",
		"variation": "default",
		"primary": {
			"heading": {
				"__TYPE__": "StructuredTextContent",
				"value": [
					{
						"type": "heading2",
						"content": {
							"text": "Farther"
						}
					}
				]
			},
			"image": {
				"url": "https://images.unsplash.com/photo-1704960945899-96c434c05264?crop=entropy&cs=srgb&fm=jpg&ixid=M3wzMzc0NjN8MHwxfHNlYXJjaHwyOHx8Y2l0cnVzJTIwZnJ1aXR8ZW58MHx8fHwxNzIzNDY4NDYwfDA&ixlib=rb-4.0.3&q=85",
				"alt": "two halves of a lemon on a white surface",
				"origin": {
					"id": "c3lGQwGCvqw",
					"url": "https://images.unsplash.com/photo-1704960945899-96c434c05264?crop=entropy&cs=srgb&fm=jpg&ixid=M3wzMzc0NjN8MHwxfHNlYXJjaHwyOHx8Y2l0cnVzJTIwZnJ1aXR8ZW58MHx8fHwxNzIzNDY4NDYwfDA&ixlib=rb-4.0.3&q=85",
					"width": 6000,
					"height": 4000
				},
				"width": 6000,
				"height": 4000,
				"edit": {
					"background": "transparent",
					"zoom": 1,
					"crop": {
						"x": 0,
						"y": 0
					}
				},
				"credits": null,
				"__TYPE__": "ImageContent",
				"thumbnails": {}
			},
			"icon": {
				"__TYPE__": "FieldContent",
				"type": "Select",
				"value": "gear"
			},
			"subheading": {
				"__TYPE__": "StructuredTextContent",
				"value": [
					{
						"type": "heading3",
						"content": {
							"text": "Break"
						}
					}
				]
			},
			"body": {
				"__TYPE__": "StructuredTextContent",
				"value": [
					{
						"type": "paragraph",
						"content": {
							"text": "Eiusmod veniam ullamco et consequat aliquip aliqua laboris est voluptate anim ad nostrud do. Est pariatur cupidatat tempor occaecat sint aliqua sint reprehenderit eu cupidatat."
						}
					}
				]
			},
			"button_link": {
				"__TYPE__": "LinkContent",
				"value": {
					"__TYPE__": "ExternalLink",
					"url": "http://twitter.com"
				}
			},
			"button_text": {
				"__TYPE__": "FieldContent",
				"value": "when",
				"type": "Text"
			}
		},
		"items": []
	},
	{
		"__TYPE__": "SharedSliceContent",
		"variation": "reverse",
		"primary": {
			"heading": {
				"__TYPE__": "StructuredTextContent",
				"value": [
					{
						"type": "heading2",
						"content": {
							"text": "Rhyme"
						}
					}
				]
			},
			"image": {
				"url": "https://images.unsplash.com/photo-1704960945899-96c434c05264?crop=entropy&cs=srgb&fm=jpg&ixid=M3wzMzc0NjN8MHwxfHNlYXJjaHwyOHx8Y2l0cnVzJTIwZnJ1aXR8ZW58MHx8fHwxNzIzNDY4NDYwfDA&ixlib=rb-4.0.3&q=85",
				"alt": "two halves of a lemon on a white surface",
				"origin": {
					"id": "c3lGQwGCvqw",
					"url": "https://images.unsplash.com/photo-1704960945899-96c434c05264?crop=entropy&cs=srgb&fm=jpg&ixid=M3wzMzc0NjN8MHwxfHNlYXJjaHwyOHx8Y2l0cnVzJTIwZnJ1aXR8ZW58MHx8fHwxNzIzNDY4NDYwfDA&ixlib=rb-4.0.3&q=85",
					"width": 6000,
					"height": 4000
				},
				"width": 6000,
				"height": 4000,
				"edit": {
					"background": "transparent",
					"zoom": 1,
					"crop": {
						"x": 0,
						"y": 0
					}
				},
				"credits": null,
				"__TYPE__": "ImageContent",
				"thumbnails": {}
			},
			"icon": {
				"__TYPE__": "FieldContent",
				"type": "Select",
				"value": "cycle"
			},
			"subheading": {
				"__TYPE__": "StructuredTextContent",
				"value": [
					{
						"type": "heading3",
						"content": {
							"text": "Anybody"
						}
					}
				]
			},
			"body": {
				"__TYPE__": "StructuredTextContent",
				"value": [
					{
						"type": "paragraph",
						"content": {
							"text": "Cupidatat velit dolore exercitation dolor ex irure nostrud anim consectetur aliqua deserunt pariatur voluptate."
						}
					}
				]
			},
			"button_link": {
				"__TYPE__": "LinkContent",
				"value": {
					"__TYPE__": "ExternalLink",
					"url": "http://google.com"
				}
			},
			"button_text": {
				"__TYPE__": "FieldContent",
				"value": "compass",
				"type": "Text"
			}
		},
		"items": [
			{
				"__TYPE__": "GroupItemContent",
				"value": []
			}
		]
	}
]